README.md
synbio_schema/__init__.py
synbio_schema-0.0.1.dist-info/LICENSE
synbio_schema-0.0.1.dist-info/WHEEL
synbio_schema-0.0.1.dist-info/METADATA
synbio_schema-0.0.1.dist-info/RECORD
