Metadata-Version: 2.1
Name: synbio-schema
Version: 0.0.1
Summary: A schema for synthetic biology, inspired by IARPA FELIX
License: MIT
Author: Mark Andrew Miller
Author-email: MAM@lbl.gov
Requires-Python: >=3.9,<4.0
Classifier: License :: OSI Approved :: MIT License
Classifier: Programming Language :: Python :: 3
Classifier: Programming Language :: Python :: 3.10
Classifier: Programming Language :: Python :: 3.9
Provides-Extra: docs
Requires-Dist: cruft (>=2.11.1,<3.0.0)
Requires-Dist: db-to-sqlite (>=1.4,<2.0)
Requires-Dist: linkml-runtime (>=1.1.24,<2.0.0)
Requires-Dist: psycopg2 (>=2.9.3,<3.0.0)
